Workbook

Sheet 01_RESUMO
E1: MIS
E3: RELATÓRIO | F3: Cliente: | G3: ='00_CONFIG'!B6 -> Banco X | H3: Operação: | I3: ='00_CONFIG'!B7 -> Vendas | K3: Período: | L3: ='00_CONFIG'!B8&" a "&'00_CONFIG'!B9 -> 01/09/2026 a 03/09/2026 | Q3: Data da Extração
E4: OPERACIONAL | Q4: ='00_CONFIG'!B12 -> 46309.5
A8: Resumo
A11: Operacional
E13: TAXAS DE ATENDIMENTO | M13: TAXAS DE ATENDIMENTO
A14: Detalhamento
A17: Indicadores | N17: ='02_OPERACIONAL'!F40 -> 0.87096926 | P17: ='02_OPERACIONAL'!G40 -> 0.94488218 | R17: ='02_OPERACIONAL'!H40 -> 0.25283298 | T17: ='02_OPERACIONAL'!I40 -> 0.84195014
A20: Base
N21: % Alô | P21: % Qualificação | R21: % Apresentação | T21: % Win Rate
E29: Meta x Realizado
E35: INDICADORES | Q35: =$G$40 -> 0.57265
E37: Indicador | F37: Meta% | G37: Atingimento | H37: Meta | I37: Resultado
E38: Atendidas | F38: 1 | G38: =I38/H38 -> 0.6325 | H38: 80000 | I38: 50600 | Q38: % Atingimento
E39: Vendas | F39: 0.99 | G39: =I39/H39 -> 0.5128 | H39: 10000 | I39: 5128
G40: =AVERAGE(G38:G39) -> 0.57265

Sheet 02_OPERACIONAL
E1: MIS
E2: ACOMPANHAMENTO OPERACIONAL
E3: Cliente: Banco X | Operação: Vendas | Período: 01/09/2026 a 03/09/2026
E5: Hora | F5: Tentativas | G5: Alô | H5: Oportunidade | I5: Propostas | J5: Vendas Fechadas | K5: % Alô | L5: % Qualificação | M5: % Apresentação | N5: Win Rate
E6: 08h | F6: 200 | G6: 182 | H6: =G6-30 -> 152 | I6: 42 | J6: =I6-20 -> 22 | K6: =G6/F6 -> 0.91 | L6: =H6/G6 -> 0.83516484 | M6: =I6/H6 -> 0.27631579 | N6: =J6/I6 -> 0.52380952 | O6: =G6/F6 -> 0.91
A7: Resumo | E7: 09h | F7: 722 | G7: 612 | H7: =G7-30 -> 582 | I7: 143 | J7: =I7-20 -> 123 | K7: =G7/F7 -> 0.84764543 | L7: =H7/G7 -> 0.95098039 | M7: =I7/H7 -> 0.24570447 | N7: =J7/I7 -> 0.86013986 | O7: =G7/F7 -> 0.84764543
E8: 10h | F8: 900 | G8: 812 | H8: =G8-30 -> 782 | I8: 194 | J8: =I8-20 -> 174 | K8: =G8/F8 -> 0.90222222 | L8: =H8/G8 -> 0.96305419 | M8: =I8/H8 -> 0.24808184 | N8: =J8/I8 -> 0.89690722 | O8: =G8/F8 -> 0.90222222
E9: 11h | F9: 1300 | G9: 1150 | H9: =G9-40 -> 1110 | I9: 276 | J9: =I9-24 -> 252 | K9: =G9/F9 -> 0.88461538 | L9: =H9/G9 -> 0.96521739 | M9: =I9/H9 -> 0.24864865 | N9: =J9/I9 -> 0.91304348 | O9: =G9/F9 -> 0.88461538
A10: Operacional | E10: 12h | F10: 1820 | G10: 1520 | H10: =G10-40 -> 1480 | I10: 368 | J10: =I10-24 -> 344 | K10: =G10/F10 -> 0.83516484 | L10: =H10/G10 -> 0.97368421 | M10: =I10/H10 -> 0.24864865 | N10: =J10/I10 -> 0.93478261 | O10: =G10/F10 -> 0.83516484
E11: 13h | F11: 1750 | G11: 1630 | H11: =G11-40 -> 1590 | I11: 392 | J11: =I11-24 -> 368 | K11: =G11/F11 -> 0.93142857 | L11: =H11/G11 -> 0.97546012 | M11: =I11/H11 -> 0.24654088 | N11: =J11/I11 -> 0.93877551 | O11: =G11/F11 -> 0.93142857
E12: 14h | F12: 1820 | G12: 1520 | H12: =G12-40 -> 1480 | I12: 360 | J12: =I12-34 -> 326 | K12: =G12/F12 -> 0.83516484 | L12: =H12/G12 -> 0.97368421 | M12: =I12/H12 -> 0.24324324 | N12: =J12/I12 -> 0.90555556 | O12: =G12/F12 -> 0.83516484
A13: Detalhamento | E13: 15h | F13: 1740 | G13: 1420 | H13: =G13-49 -> 1371 | I13: 334 | J13: =I13-34 -> 300 | K13: =G13/F13 -> 0.81609195 | L13: =H13/G13 -> 0.96549296 | M13: =I13/H13 -> 0.2436178 | N13: =J13/I13 -> 0.89820359 | O13: =G13/F13 -> 0.81609195
E14: 16h | F14: 1100 | G14: 1080 | H14: =G14-49 -> 1031 | I14: 258 | J14: =I14-47 -> 211 | K14: =G14/F14 -> 0.98181818 | L14: =H14/G14 -> 0.95462963 | M14: =I14/H14 -> 0.25024248 | N14: =J14/I14 -> 0.81782946 | O14: =G14/F14 -> 0.98181818
E15: 17h | F15: 941 | G15: 760 | H15: =G15-49 -> 711 | I15: 174 | J15: =I15-47 -> 127 | K15: =G15/F15 -> 0.80765143 | L15: =H15/G15 -> 0.93552632 | M15: =I15/H15 -> 0.24472574 | N15: =J15/I15 -> 0.72988506 | O15: =G15/F15 -> 0.80765143
A16: Indicadores | E16: 18h | F16: 596 | G16: 494 | H16: =G16-49 -> 445 | I16: 127 | J16: =I16-20 -> 107 | K16: =G16/F16 -> 0.82885906 | L16: =H16/G16 -> 0.90080972 | M16: =I16/H16 -> 0.28539326 | N16: =J16/I16 -> 0.84251969 | O16: =G16/F16 -> 0.82885906
E17: TOTAL | F17: =SUM(F6:F16) -> 12889 | G17: =SUM(G6:G16) -> 11180 | H17: =SUM(H6:H16) -> 10734 | I17: =SUM(I6:I16) -> 2668 | J17: =SUM(J6:J16) -> 2354 | K17: =AVERAGE(K6:K16) -> 0.87096926 | L17: =AVERAGE(L6:L16) -> 0.94488218 | M17: =AVERAGE(M6:M16) -> 0.25283298 | N17: =AVERAGE(N6:N16) -> 0.84195014
A19: Base
F38: % Alô | G38: % Qualificação | H38: % Apresentação | I38: Win Rate | J38: % Atingimento
E39: Meta | F39: 0.99 | G39: 0.1 | H39: 0.99 | I39: 1 | J39: =AVERAGE(F39:I39) -> 0.77
E40: Realizado | F40: =K17 -> 0.87096926 | G40: =L17 -> 0.94488218 | H40: =M17 -> 0.25283298 | I40: =N17 -> 0.84195014 | J40: =AVERAGE(F40:I40) -> 0.72765864
E44: % Alô | F44: 0.99 | G44: 1
E45: % Qualificação | F45: 0.1 | G45: 1
E46: % Apresentação | F46: 0.99 | G46: 1
E47: Win Rate | F47: 1 | G47: 1

Sheet 03_DETALHAMENTO
E1: MIS
E2: DETALHAMENTO OPERACIONAL
E3: Cliente: Banco X | Operação: Vendas | Período: 01/09/2026 a 03/09/2026
E5: Data | F5: Canal / Produto / Operador | G5: Leads | H5: Alô | I5: Oportunidades | J5: Propostas | K5: Vendas | L5: Conversão % | M5: Ticket Médio | N5: Receita Total
E6: 03/09/2026 | F6: Outbound / Discador | G6: 15000 | H6: 4200 | I6: 850 | J6: 520 | K6: 130 | L6: 0.0087 | M6: 450 | N6: 58500
A7: Resumo | E7: 03/09/2026 | F7: Inbound / Receptivo | G7: 3500 | H7: 3100 | I7: 1200 | J7: 980 | K7: 340 | L7: 0.0971 | M7: 520 | N7: 176800
E8: 03/09/2026 | F8: WhatsApp / Bot | G8: 8000 | H8: 5600 | I8: 1800 | J8: 1100 | K8: 210 | L8: 0.0263 | M8: 390 | N8: 81900
A10: Operacional
A13: Detalhamento
A16: Indicadores
A19: Base

Sheet 04_INDICADORES
E1: MIS
E2: DICIONÁRIO DE INDICADORES
E3: Cliente: Banco X | Operação: Vendas | Período: 01/09/2026 a 03/09/2026
E5: Indicador | F5: Definição | G5: Fórmula / Regra | H5: Unidade | I5: Fonte | J5: Observações
E6: Leads / Contatos | F6: Total de novos leads recebidos / carregados na base. | G6: Soma de Qtde | H6: Volume | I6: SQL | J6: Inclui todos os contratos ativos para discagem
A7: Resumo | E7: Alô | F7: Contato efetivo | G7: Regra de Alô homologada | H7: Volume | I7: SQL | J7: Volume de chamadas efetivamente atendidas por operadores.
E8: Oportunidades | F8: Leads qualificados pelo operador (demonstraram interesse real). | G8: Status definidos | H8: Volume | I8: SQL | J8: Volume de chamadas com status de interesse
E9: Qualificação | F9: % de alô que demonstrou interesse | G9: Oportunidades / Alô | H9: % | I9: SQL | J9: Volume de chamadas com status de interesse
A10: Operacional | E10: Propostas Enviadas | F10: Orçamentos ou propostas formais apresentadas aos clientes. | G10: Status definidos | H10: Volume | I10: SQL | J10: Volume de chamadas com status de Proposta
E11: Apresentação | F11: % de oportunidades que receberam oferta | G11: Propostas / Oportunidades | H11: % | I11: SQL | Q11: Conversão % | R11: Total de Vendas / Total de Leads (ou % Alô → Vendas). | S11: Total de Vendas / Total de Leads | T11: %
E12: Vendas Realizadas | F12: Total de negócios fechados / contratos assinados. | G12: Status definidos | H12: Volume | I12: SQL | J12: Volume de Propostas Fechadas
A13: Detalhamento | E13: Fechamento (Win Rate) | F13: % de propostas que viraram venda | G13: Vendas / Propostas | H13: % | I13: SQL
E14: Receita Total | F14: Faturamento bruto gerado no período | G14: Total de Vendas × Ticket Médio | H14: $ | I14: SQL
E15: Ticket Médio | F15: Valor médio por venda | G15: Receita Total / Total de Vendas | H15: $ | I15: SQL
A16: Indicadores | E16: TMA | F16: Tempo médio de atendimento | G16: Média do tempo de atendimento | H16: Tempo | I16: SQL | J16: Formato hh:mm:ss
E17: TME | F17: Tempo médio de espera | G17: Média Espera | H17: Tempo | I17: SQL | J17: Formato hh:mm:ss
A19: Base

Sheet 05_BASE
E1: MIS
E2: BASE | DADOS TÉCNICOS
E3: Cliente: Banco X | Operação: Vendas | Período: 01/09/2026 a 03/09/2026
E5: Data | F5: Hora | G5: Operador | H5: Equipe | I5: Tabulação | J5: Subtabulação | K5: Qtde | L5: TMA | M5: TME
E6: 03/09/2026 | F6: 08h | G6: Operador A | H6: Equipe 01 | I6: SUCESSO | J6: Proposta Enviada | K6: 10 | L6: 00:02:31 | M6: 00:00:12
A7: Resumo | E7: 03/09/2026 | F7: 08h | G7: Operador B | H7: Equipe 02 | I7: SUCESSO | J7: Venda Concluída | K7: 8 | L7: 00:03:04 | M7: 00:00:18
E8: 03/09/2026 | F8: 09h | G8: Operador C | H8: Equipe 03 | I8: SUCESSO | J8: Alteração Cadastral | K8: 12 | L8: 00:02:45 | M8: 00:00:15
A10: Operacional
A13: Detalhamento
A16: Indicadores
A19: Base

Sheet 00_CONFIG
A1: DBM | MIS
A2: CONFIGURAÇÃO | USO INTERNO MIS
A3: Cliente: Banco X | Operação: Cobrança | Período: 01/09/2026 a 03/09/2026
A5: Campo | B5: Valor
A6: Cliente | B6: Banco X
A7: Operação | B7: Vendas
A8: Período Inicial | B8: 01/09/2026
A9: Período Final | B9: 03/09/2026
A10: Responsável MIS | B10: Nome do Analista
A11: Versão | B11: v1.0
A12: Última Atualização | B12: 46309.5
